gem_metrics_fork/__init__.py
gem_metrics_fork/bertscore.py
gem_metrics_fork/bleu.py
gem_metrics_fork/bleurt.py
gem_metrics_fork/chrf.py
gem_metrics_fork/cider.py
gem_metrics_fork/config.py
gem_metrics_fork/data.py
gem_metrics_fork/local_recall.py
gem_metrics_fork/meteor.py
gem_metrics_fork/metric.py
gem_metrics_fork/moverscore.py
gem_metrics_fork/msttr.py
gem_metrics_fork/ngrams.py
gem_metrics_fork/nist.py
gem_metrics_fork/nubia.py
gem_metrics_fork/prism.py
gem_metrics_fork/questeval.py
gem_metrics_fork/rouge.py
gem_metrics_fork/sari.py
gem_metrics_fork/ter.py
gem_metrics_fork/texts.py
gem_metrics_fork/tokenize.py
gem_metrics_fork/ttr.py
gem_metrics_fork/wer.py
gem_metrics_fork/yules_i.py
gem_metrics_fork/impl/__init__.py
gem_metrics_fork/impl/meteor.py
gem_metrics_fork/impl/pymteval.py
gem_metrics_fork-0.1.dev0.dist-info/LICENSE
gem_metrics_fork-0.1.dev0.dist-info/METADATA
gem_metrics_fork-0.1.dev0.dist-info/WHEEL
gem_metrics_fork-0.1.dev0.dist-info/top_level.txt
gem_metrics_fork-0.1.dev0.dist-info/RECORD
