Metadata-Version: 2.1
Name: gem-metrics-fork
Version: 0.1.dev0
Summary: GEM Challenge metrics
License-File: LICENSE
Requires-Dist: datasets >=1.2.1
Requires-Dist: diskcache >=5.2.1
Requires-Dist: nltk
Requires-Dist: numpy
Requires-Dist: rouge-score
Requires-Dist: logzero
Requires-Dist: pycountry
Requires-Dist: repro ==0.1.4
Requires-Dist: sacrebleu >=2.0.0
Requires-Dist: sacremoses
